easy_sm/__init__.py
easy_sm/__main__.py
easy_sm/commands/__init__.py
easy_sm/commands/build.py
easy_sm/commands/cloud.py
easy_sm/commands/helpers.py
easy_sm/commands/initialize.py
easy_sm/commands/local.py
easy_sm/commands/push.py
easy_sm/config/__init__.py
easy_sm/config/config.py
easy_sm/sagemaker/__init__.py
easy_sm/sagemaker/sagemaker.py
easy_sm/template/__init__.py
easy_sm/template/easy_sm_base/Dockerfile
easy_sm/template/easy_sm_base/__init__.py
easy_sm/template/easy_sm_base/build.sh
easy_sm/template/easy_sm_base/executor.sh
easy_sm/template/easy_sm_base/push.sh
easy_sm/template/easy_sm_base/local_test/deploy_local.sh
easy_sm/template/easy_sm_base/local_test/make_local.sh
easy_sm/template/easy_sm_base/local_test/process_local.sh
easy_sm/template/easy_sm_base/local_test/train_local.sh
easy_sm/template/easy_sm_base/local_test/test_dir/input/data/training/.gitkeep
easy_sm/template/easy_sm_base/local_test/test_dir/model/.gitkeep
easy_sm/template/easy_sm_base/local_test/test_dir/output/.gitkeep
easy_sm/template/easy_sm_base/prediction/__init__.py
easy_sm/template/easy_sm_base/prediction/serve
easy_sm/template/easy_sm_base/processing/__init__.py
easy_sm/template/easy_sm_base/training/__init__.py
easy_sm/template/easy_sm_base/training/train
easy_sm/template/easy_sm_base/training/training.py
easy_sm-0.1.12.dist-info/LICENSE
easy_sm-0.1.12.dist-info/METADATA
easy_sm-0.1.12.dist-info/WHEEL
easy_sm-0.1.12.dist-info/entry_points.txt
easy_sm-0.1.12.dist-info/top_level.txt
easy_sm-0.1.12.dist-info/RECORD
